simple_gdrive/__init__.py
simple_gdrive/__main__.py
simple_gdrive/auth.py
simple_gdrive/config.py
simple_gdrive/fs.py
simple_gdrive-1.1.2.dist-info/entry_points.txt
simple_gdrive-1.1.2.dist-info/LICENSE
simple_gdrive-1.1.2.dist-info/WHEEL
simple_gdrive-1.1.2.dist-info/METADATA
simple_gdrive-1.1.2.dist-info/RECORD
